chancleta/__init__.py
chancleta/parser.py
chancleta-1.0.3.dist-info/LICENSE
chancleta-1.0.3.dist-info/METADATA
chancleta-1.0.3.dist-info/WHEEL
chancleta-1.0.3.dist-info/RECORD
