Metadata-Version: 2.3
Name: chancleta
Version: 1.0.3
Summary: Python library for creating Command Line Interfaces via configuration files. Supports .toml, .json, .yaml and .xml (for the brave ones)
Home-page: https://github.com/kaliv0/chancleta.git
License: LICENSE
Keywords: command line interface,cli starter kit,toml,json,yaml,xml
Author: kaliv0
Author-email: kaloyan.ivanov88@gmail.com
Requires-Python: >=3.12,<4.0
Classifier: License :: Other/Proprietary License
Classifier: Programming Language :: Python :: 3
Classifier: Programming Language :: Python :: 3.12
Classifier: Programming Language :: Python :: 3.13
Requires-Dist: pyyaml (>=6.0.2,<7.0.0)
Requires-Dist: xmltodict (>=0.13.0,<0.14.0)
Project-URL: Repository, https://github.com/kaliv0/chancleta.git
